Vho/__init__.py
Vho/foto.py
Vho/text.py
Vho/video.py
vho-0.3.8.dist-info/licenses/LICENSE
vho-0.3.8.dist-info/METADATA
vho-0.3.8.dist-info/WHEEL
vho-0.3.8.dist-info/top_level.txt
vho-0.3.8.dist-info/RECORD
