Metadata-Version: 2.4
Name: Vho
Version: 0.3.8
Summary: Vho: İşlevsel ve kolaylaştırılmış görsel oluşturma kütüphanesi
Author: Bedirhan
Author-email: bedirhan.oytpass@gmail.com
License: MIT
Keywords: görsel,kolay,basitleştirilmiş
Classifier: License :: OSI Approved :: MIT License
Classifier: Programming Language :: Python :: 3
Classifier: Programming Language :: Python :: 3.6
Classifier: Programming Language :: Python :: 3.7
Classifier: Programming Language :: Python :: 3.8
Classifier: Programming Language :: Python :: 3.9
Classifier: Programming Language :: Python :: 3.10
License-File: LICENSE
Requires-Dist: torch
Requires-Dist: diffusers>=0.24.0
Requires-Dist: torchvision
Requires-Dist: controlnet-aux
Requires-Dist: opencv-python
Requires-Dist: transformers>=4.35.0
Requires-Dist: accelerate>=0.25.0
Requires-Dist: safetensors>=0.4.0
Requires-Dist: imageio>=2.31.0
Requires-Dist: imageio-ffmpeg>=0.4.9
Requires-Dist: deep-translator>=1.11.4
Requires-Dist: numpy
Requires-Dist: Pillow
Dynamic: author
Dynamic: author-email
Dynamic: classifier
Dynamic: description
Dynamic: description-content-type
Dynamic: keywords
Dynamic: license
Dynamic: license-file
Dynamic: requires-dist
Dynamic: summary
